ftta/__init__.py
ftta/_ftta.cpython-37m-darwin.so
ftta/context.py
ftta/draw.py
ftta-0.1.0.dist-info/METADATA
ftta-0.1.0.dist-info/WHEEL
ftta-0.1.0.dist-info/top_level.txt
ftta-0.1.0.dist-info/RECORD
